atkspy/Colloquial_Converter.py
atkspy/Diacritizer.py
atkspy/Named_Entity_Recognizer.py
atkspy/Parser.py
atkspy/Part_of_Speech_Tagger.py
atkspy/SARF.py
atkspy/Speller.py
atkspy/Transliteration.py
atkspy/__init__.py
atkspy-0.5.1.dist-info/DESCRIPTION.rst
atkspy-0.5.1.dist-info/METADATA
atkspy-0.5.1.dist-info/RECORD
atkspy-0.5.1.dist-info/WHEEL
atkspy-0.5.1.dist-info/metadata.json
atkspy-0.5.1.dist-info/top_level.txt
