Metadata-Version: 2.0
Name: atkspy
Version: 0.5.1
Summary: A python package that supports SOAP interface to communicate with the Microsoft ATKS
Home-page: https://github.com/AliAbdelaal/ATKSpy
Author: Ali Abdelaal
Author-email: aliabdelaal369@gmail.com
License: MIT
Platform: UNKNOWN
Requires-Python: >=3
Requires-Dist: zeep
